README.md
setup.cfg
setup.py
atlas_metadata_extractor.egg-info/PKG-INFO
atlas_metadata_extractor.egg-info/SOURCES.txt
atlas_metadata_extractor.egg-info/dependency_links.txt
atlas_metadata_extractor.egg-info/requires.txt
atlas_metadata_extractor.egg-info/top_level.txt
examples/__init__.py
metadata_extractor/__init__.py
metadata_extractor/builders/__init__.py
metadata_extractor/builders/rdbms/__init__.py
metadata_extractor/builders/rdbms/mariadb_builder.py
metadata_extractor/builders/rdbms/mysql_builder.py
metadata_extractor/builders/rdbms/postgresql_builder.py
metadata_extractor/builders/rdbms/rdbms_builder_abstract.py
metadata_extractor/builders/rdbms/redshift_builder.py
metadata_extractor/connection/__init__.py
metadata_extractor/connection/connection_abstract.py
metadata_extractor/connection/rdbms/__init__.py
metadata_extractor/connection/rdbms/mysql_connection.py
metadata_extractor/connection/rdbms/postgresql_connection.py
metadata_extractor/extractor/__init__.py
metadata_extractor/extractor/rdbms/__init__.py
metadata_extractor/extractor/rdbms/mysql_extractor.py
metadata_extractor/extractor/rdbms/postgresql_extractor.py
metadata_extractor/extractor/rdbms/rdbms_extractor_abstract.py
metadata_extractor/factories/__init__.py
metadata_extractor/factories/builder_factory.py
metadata_extractor/factories/connection_factory.py
metadata_extractor/factories/extractor_factory.py
metadata_extractor/models/__init__.py
metadata_extractor/models/atlas_model/__init__.py
metadata_extractor/models/atlas_model/rdbms/__init__.py
metadata_extractor/models/atlas_model/rdbms/column_info.py
metadata_extractor/models/atlas_model/rdbms/database_info.py
metadata_extractor/models/atlas_model/rdbms/database_schema.py
metadata_extractor/models/atlas_model/rdbms/rdbms_instance.py
metadata_extractor/models/atlas_model/rdbms/table_info.py
metadata_extractor/models/enum/__init__.py
metadata_extractor/models/enum/db_engine_enum.py
metadata_extractor/models/hosts/__init__.py
metadata_extractor/models/hosts/rdbms_host.py
metadata_extractor/pipeline/__init__.py
metadata_extractor/pipeline/rdbms_pipeline.py
metadata_extractor/publisher/__init__.py
metadata_extractor/publisher/atlas_publisher.py
