Metadata-Version: 1.1
Name: atlas-metadata-extractor
Version: 0.0.5
Summary: This project is used for extract metadata from data source
Home-page: https://github.com/pongthep/atlas-metadata-extractor
Author: pongthepv
Author-email: mr.pongthep@gmail.com
License: MIT
Download-URL: https://github.com/pongthep/atlas-metadata-extractor/archive/v0.0.5.tar.gz
Keywords: apache atlas,atlas,extractor
Platform: UNKNOWN
Classifier: Development Status :: 3 - Alpha
Classifier: Intended Audience :: Developers
Classifier: Topic :: Software Development :: Build Tools
Classifier: License :: OSI Approved :: MIT License
Classifier: Programming Language :: Python :: 3.6
